drf_action_params_validator/__init__.py
drf_action_params_validator-0.0.4.dist-info/LICENCE
drf_action_params_validator-0.0.4.dist-info/METADATA
drf_action_params_validator-0.0.4.dist-info/WHEEL
drf_action_params_validator-0.0.4.dist-info/top_level.txt
drf_action_params_validator-0.0.4.dist-info/RECORD
