Metadata-Version: 2.1
Name: drf-action-params-validator
Version: 0.0.4
Summary: A small validator for params in drf view actions
Home-page: https://github.com/klymenok/drf-params-validator
Author: Oleksii Klymenok
Author-email: klymenok.a@gmail.com
License: UNKNOWN
Platform: UNKNOWN
Classifier: Programming Language :: Python :: 3
Classifier: License :: OSI Approved :: MIT License
Classifier: Operating System :: OS Independent
Requires-Python: >=3.6
Requires-Dist: Django (>=2.2.0)
Requires-Dist: djangorestframework (>=3.11.0)
